sysinfo/__init__.py
sysinfo/core.py
sysinfo_collector-0.2.5.dist-info/licenses/LICENSE
sysinfo_collector-0.2.5.dist-info/METADATA
sysinfo_collector-0.2.5.dist-info/WHEEL
sysinfo_collector-0.2.5.dist-info/top_level.txt
sysinfo_collector-0.2.5.dist-info/RECORD
