Metadata-Version: 2.4
Name: sysinfo-collector
Version: 0.2.5
Summary: 一个获取macOS电脑信息的Python包
Author-email: yuanni <1911398892@qq.com>
License: MIT License
Project-URL: Homepage, https://gitee.com/KAERBluetooth/my_uv_project.git
Project-URL: Repository, https://gitee.com/KAERBluetooth/my_uv_project.git
Project-URL: Documentation, https://gitee.com/KAERBluetooth/my_uv_project.git
Classifier: Programming Language :: Python :: 3
Classifier: License :: OSI Approved :: MIT License
Classifier: Operating System :: OS Independent
Classifier: Topic :: System :: Systems Administration
Requires-Python: >=3.11
License-File: LICENSE
Requires-Dist: psutil>=7.0.0
Requires-Dist: twine>=6.1.0
Dynamic: license-file
